emotionics/__init__.py
emotionics/core.py
emotionics/errors.py
emotionics/lite.py
emotionics/schema.py
emotionics/providers/__init__.py
emotionics/providers/openai.py
emotionics-0.1.1.dist-info/METADATA
emotionics-0.1.1.dist-info/WHEEL
emotionics-0.1.1.dist-info/top_level.txt
emotionics-0.1.1.dist-info/RECORD
