Metadata-Version: 2.4
Name: emotionics
Version: 0.1.1
Summary: Emotionics API (Python library)
Author: Kouhei Takagi
License-Expression: MIT
Project-URL: Homepage, https://github.com/Kouhei-Takagi/emotionics
Project-URL: Documentation, https://github.com/Kouhei-Takagi/emotionics#readme
Project-URL: Source, https://github.com/Kouhei-Takagi/emotionics
Project-URL: Issues, https://github.com/Kouhei-Takagi/emotionics/issues
Requires-Python: >=3.10
